{
  "0": {
    "0": { "48": { "0": "Portal" } },
    "1": { "40": { "0": "Portal" } },
    "2": { "60": { "0": "Portal" } },
    "3": { "24": { "0": "Portal" } },
    "4": { "14": { "1": "Portal" } }
  },
  "1": {
    "0": { "49": { "0": "Portal" } },
    "1": { "41": { "0": "Portal" } },
    "2": { "61": { "0": "Portal" } },
    "3": { "25": { "0": "Portal" } },
    "4": { "15": { "1": "Portal" } }
  },
  "10": {
    "0": { "58": { "0": "Portal" } },
    "1": { "38": { "0": "Portal" } },
    "2": { "68": { "0": "Portal" } },
    "3": { "32": { "0": "Portal" } },
    "4": { "21": { "1": "Portal" } }
  },
  "11": {
    "0": { "59": { "0": "Portal" } },
    "1": { "39": { "0": "Portal" } },
    "2": { "69": { "0": "Portal" } },
    "3": { "33": { "0": "Portal" } },
    "4": { "20": { "1": "Portal" } }
  },
  "12": {
    "0": { "14": { "0": "Portal" } },
    "2": { "72": { "1": "Portal" } }
  },
  "13": {
    "0": { "15": { "0": "Portal" } },
    "2": { "73": { "1": "Portal" } }
  },
  "14": { "2": { "74": { "1": "Portal" } } },
  "15": { "2": { "75": { "1": "Portal" } } },
  "16": {
    "0": { "17": { "0": "Portal" } },
    "2": { "76": { "1": "Portal" } }
  },
  "17": { "2": { "77": { "1": "Portal" } } },
  "18": {
    "0": { "19": { "0": "Portal" } },
    "2": { "78": { "1": "Portal" } }
  },
  "19": { "2": { "79": { "1": "Portal" } } },
  "2": {
    "0": { "50": { "0": "Portal" } },
    "1": { "42": { "0": "Portal" } },
    "2": { "62": { "0": "Portal" } },
    "3": { "26": { "0": "Portal" } },
    "4": { "12": { "1": "Portal" } }
  },
  "20": {
    "0": { "23": { "0": "Portal" } },
    "2": { "80": { "1": "Portal" } }
  },
  "21": {
    "0": { "22": { "0": "Portal" } },
    "2": { "81": { "1": "Portal" } }
  },
  "22": { "2": { "82": { "1": "Portal" } } },
  "23": { "2": { "83": { "1": "Portal" } } },
  "24": {
    "1": { "88": { "2": "Portal" } },
    "2": { "68": { "2": "Portal" } }
  },
  "25": {
    "1": { "89": { "2": "Portal" } },
    "2": { "69": { "2": "Portal" } }
  },
  "26": {
    "1": { "90": { "2": "Portal" } },
    "2": { "70": { "2": "Portal" } }
  },
  "27": {
    "1": { "91": { "2": "Portal" } },
    "2": { "71": { "2": "Portal" } }
  },
  "28": {
    "1": { "88": { "0": "Portal" } },
    "2": { "60": { "2": "Portal" } }
  },
  "29": {
    "1": { "89": { "0": "Portal" } },
    "2": { "61": { "2": "Portal" } }
  },
  "3": {
    "0": { "51": { "0": "Portal" } },
    "1": { "43": { "0": "Portal" } },
    "2": { "63": { "0": "Portal" } },
    "3": { "27": { "0": "Portal" } },
    "4": { "13": { "1": "Portal" } }
  },
  "30": {
    "1": { "90": { "0": "Portal" } },
    "2": { "62": { "2": "Portal" } }
  },
  "31": {
    "1": { "91": { "0": "Portal" } },
    "2": { "63": { "2": "Portal" } }
  },
  "32": {
    "1": { "88": { "1": "Portal" } },
    "2": { "64": { "2": "Portal" } }
  },
  "33": {
    "1": { "89": { "1": "Portal" } },
    "2": { "65": { "2": "Portal" } }
  },
  "34": {
    "1": { "90": { "1": "Portal" } },
    "2": { "66": { "2": "Portal" } }
  },
  "35": {
    "1": { "91": { "1": "Portal" } },
    "2": { "67": { "2": "Portal" } }
  },
  "36": {
    "1": { "84": { "0": "Portal" } },
    "2": { "48": { "2": "Portal" } }
  },
  "37": {
    "1": { "85": { "0": "Portal" } },
    "2": { "49": { "2": "Portal" } }
  },
  "38": {
    "1": { "86": { "0": "Portal" } },
    "2": { "50": { "2": "Portal" } }
  },
  "39": {
    "1": { "87": { "0": "Portal" } },
    "2": { "51": { "2": "Portal" } }
  },
  "4": {
    "0": { "52": { "0": "Portal" } },
    "1": { "44": { "0": "Portal" } },
    "2": { "65": { "0": "Portal" } },
    "3": { "29": { "0": "Portal" } },
    "4": { "17": { "1": "Portal" } }
  },
  "40": {
    "1": { "84": { "2": "Portal" } },
    "2": { "52": { "2": "Portal" } }
  },
  "41": {
    "1": { "85": { "2": "Portal" } },
    "2": { "53": { "2": "Portal" } }
  },
  "42": {
    "1": { "86": { "2": "Portal" } },
    "2": { "54": { "2": "Portal" } }
  },
  "43": {
    "1": { "87": { "2": "Portal" } },
    "2": { "55": { "2": "Portal" } }
  },
  "44": {
    "1": { "84": { "1": "Portal" } },
    "2": { "56": { "2": "Portal" } }
  },
  "45": {
    "1": { "85": { "1": "Portal" } },
    "2": { "57": { "2": "Portal" } }
  },
  "46": {
    "1": { "86": { "1": "Portal" } },
    "2": { "58": { "2": "Portal" } }
  },
  "47": {
    "1": { "87": { "1": "Portal" } },
    "2": { "59": { "2": "Portal" } }
  },
  "48": { "1": { "72": { "0": "Portal" } } },
  "49": { "1": { "73": { "0": "Portal" } } },
  "5": {
    "0": { "53": { "0": "Portal" } },
    "1": { "45": { "0": "Portal" } },
    "2": { "64": { "0": "Portal" } },
    "3": { "28": { "0": "Portal" } },
    "4": { "16": { "1": "Portal" } }
  },
  "50": { "1": { "74": { "0": "Portal" } } },
  "51": { "1": { "75": { "0": "Portal" } } },
  "52": { "1": { "76": { "0": "Portal" } } },
  "53": { "1": { "77": { "0": "Portal" } } },
  "54": { "1": { "78": { "0": "Portal" } } },
  "55": { "1": { "79": { "0": "Portal" } } },
  "56": { "1": { "80": { "0": "Portal" } } },
  "57": { "1": { "81": { "0": "Portal" } } },
  "58": { "1": { "82": { "0": "Portal" } } },
  "59": { "1": { "83": { "0": "Portal" } } },
  "6": {
    "0": { "54": { "0": "Portal" } },
    "1": { "46": { "0": "Portal" } },
    "2": { "67": { "0": "Portal" } },
    "3": { "31": { "0": "Portal" } },
    "4": { "19": { "1": "Portal" } }
  },
  "60": { "1": { "76": { "2": "Portal" } } },
  "61": { "1": { "77": { "2": "Portal" } } },
  "62": { "1": { "78": { "2": "Portal" } } },
  "63": { "1": { "79": { "2": "Portal" } } },
  "64": { "1": { "81": { "2": "Portal" } } },
  "65": { "1": { "80": { "2": "Portal" } } },
  "66": { "1": { "83": { "2": "Portal" } } },
  "67": { "1": { "82": { "2": "Portal" } } },
  "68": { "1": { "74": { "2": "Portal" } } },
  "69": { "1": { "75": { "2": "Portal" } } },
  "7": {
    "0": { "55": { "0": "Portal" } },
    "1": { "47": { "0": "Portal" } },
    "2": { "66": { "0": "Portal" } },
    "3": { "30": { "0": "Portal" } },
    "4": { "18": { "1": "Portal" } }
  },
  "70": { "1": { "72": { "2": "Portal" } } },
  "71": { "1": { "73": { "2": "Portal" } } },
  "8": {
    "0": { "56": { "0": "Portal" } },
    "1": { "36": { "0": "Portal" } },
    "2": { "70": { "0": "Portal" } },
    "3": { "34": { "0": "Portal" } },
    "4": { "23": { "1": "Portal" } }
  },
  "9": {
    "0": { "57": { "0": "Portal" } },
    "1": { "37": { "0": "Portal" } },
    "2": { "71": { "0": "Portal" } },
    "3": { "35": { "0": "Portal" } },
    "4": { "22": { "1": "Portal" } }
  }
}