{
  "0": {
    "0": { "2": { "3": "Portal" } },
    "1": { "8": { "1": "Portal" } },
    "2": { "32": { "1": "Portal" } },
    "3": { "1": { "0": "Portal" } }
  },
  "1": {
    "1": { "4": { "1": "Portal" } },
    "2": { "40": { "1": "Portal" } },
    "3": { "2": { "0": "Portal" } }
  },
  "10": {
    "2": { "44": { "1": "Portal" } },
    "3": { "11": { "0": "Portal" } }
  },
  "11": {
    "1": { "21": { "1": "Portal" } },
    "2": { "28": { "1": "Portal" } }
  },
  "12": {
    "0": { "14": { "3": "Portal" } },
    "2": { "43": { "1": "Portal" } },
    "3": { "13": { "0": "Portal" } }
  },
  "13": {
    "1": { "16": { "1": "Portal" } },
    "2": { "37": { "1": "Portal" } },
    "3": { "14": { "0": "Portal" } }
  },
  "14": {
    "1": { "18": { "1": "Portal" } },
    "2": { "25": { "1": "Portal" } }
  },
  "15": {
    "0": { "17": { "3": "Portal" } },
    "1": { "23": { "1": "Portal" } },
    "2": { "38": { "1": "Portal" } },
    "3": { "16": { "0": "Portal" } }
  },
  "16": {
    "2": { "42": { "1": "Portal" } },
    "3": { "17": { "0": "Portal" } }
  },
  "17": { "2": { "30": { "1": "Portal" } } },
  "18": {
    "0": { "20": { "3": "Portal" } },
    "2": { "36": { "1": "Portal" } },
    "3": { "19": { "0": "Portal" } }
  },
  "19": {
    "1": { "22": { "1": "Portal" } },
    "2": { "46": { "1": "Portal" } },
    "3": { "20": { "0": "Portal" } }
  },
  "2": {
    "1": { "12": { "1": "Portal" } },
    "2": { "24": { "1": "Portal" } }
  },
  "20": { "2": { "26": { "1": "Portal" } } },
  "21": {
    "0": { "23": { "3": "Portal" } },
    "2": { "47": { "1": "Portal" } },
    "3": { "22": { "0": "Portal" } }
  },
  "22": {
    "2": { "39": { "1": "Portal" } },
    "3": { "23": { "0": "Portal" } }
  },
  "23": { "2": { "29": { "1": "Portal" } } },
  "24": {
    "0": { "27": { "2": "Portal" } },
    "2": { "25": { "0": "Portal" } }
  },
  "25": { "2": { "26": { "0": "Portal" } } },
  "26": { "2": { "27": { "0": "Portal" } } },
  "28": {
    "0": { "31": { "2": "Portal" } },
    "2": { "29": { "0": "Portal" } }
  },
  "29": { "2": { "30": { "0": "Portal" } } },
  "3": {
    "0": { "5": { "3": "Portal" } },
    "1": { "17": { "1": "Portal" } },
    "2": { "41": { "1": "Portal" } },
    "3": { "4": { "0": "Portal" } }
  },
  "30": { "2": { "31": { "0": "Portal" } } },
  "32": {
    "0": { "35": { "2": "Portal" } },
    "2": { "33": { "0": "Portal" } }
  },
  "33": { "2": { "34": { "0": "Portal" } } },
  "34": { "2": { "35": { "0": "Portal" } } },
  "36": {
    "0": { "39": { "2": "Portal" } },
    "2": { "37": { "0": "Portal" } }
  },
  "37": { "2": { "38": { "0": "Portal" } } },
  "38": { "2": { "39": { "0": "Portal" } } },
  "4": {
    "2": { "35": { "1": "Portal" } },
    "3": { "5": { "0": "Portal" } }
  },
  "40": {
    "0": { "43": { "2": "Portal" } },
    "2": { "41": { "0": "Portal" } }
  },
  "41": { "2": { "42": { "0": "Portal" } } },
  "42": { "2": { "43": { "0": "Portal" } } },
  "44": {
    "0": { "47": { "2": "Portal" } },
    "2": { "45": { "0": "Portal" } }
  },
  "45": { "2": { "46": { "0": "Portal" } } },
  "46": { "2": { "47": { "0": "Portal" } } },
  "5": {
    "1": { "9": { "1": "Portal" } },
    "2": { "31": { "1": "Portal" } }
  },
  "6": {
    "0": { "8": { "3": "Portal" } },
    "1": { "20": { "1": "Portal" } },
    "2": { "45": { "1": "Portal" } },
    "3": { "7": { "0": "Portal" } }
  },
  "7": {
    "1": { "10": { "1": "Portal" } },
    "2": { "33": { "1": "Portal" } },
    "3": { "8": { "0": "Portal" } }
  },
  "8": { "2": { "27": { "1": "Portal" } } },
  "9": {
    "0": { "11": { "3": "Portal" } },
    "2": { "34": { "1": "Portal" } },
    "3": { "10": { "0": "Portal" } }
  }
}